aether/Sky.py
aether/__init__.py
aether/aether_client.py
aether/aether_sdk_config.py
aether/aetheruserconfig.py
aether/app_io_utilities.py
aether/sky_utils.py
aether/base/AppSupport.py
aether/base/GeoTiffResource.py
aether/base/QueryParameter.py
aether/base/__init__.py
aether/base/placeholder/Placeholder.py
aether/base/placeholder/PlaceholderPolygon.py
aether/base/placeholder/PlaceholderSpacetime.py
aether/base/placeholder/PlaceholderSpacetimeBuilder.py
aether/base/placeholder/__init__.py
aether/dataobjects/AEFeatureCollection.py
aether/dataobjects/AEPolygon.py
aether/dataobjects/Spacetime.py
aether/dataobjects/SpacetimeDynamic.py
aether/dataobjects/SpacetimeMixins.py
aether/dataobjects/__init__.py
aether/proto/__init__.py
aether/proto/api_pb2.py
aether/services/AppSupportServices.py
aether/services/SkyApplicationFrameworkServices.py
aether/services/UserAdminServices.py
aether/services/__init__.py
aether/session/Exceptions.py
aether/session/GlobalConfig.py
aether/session/SkySession.py
aether/session/__init__.py
aether/user_utils/HelpfulFilters.py
aether/user_utils/__init__.py
aether_shared/__init__.py
aether_shared/api_global_objects.py
aether_shared/sharedconfig.py
aether_shared/base/__init__.py
aether_shared/cloud/__init__.py
aether_shared/cloud/bigquery_io.py
aether_shared/cloud/email_io.py
aether_shared/cloud/google_cloud_storage_io.py
aether_shared/cloud/google_firebase.py
aether_shared/cloud/universal_filemanager.py
aether_shared/utilities/__init__.py
aether_shared/utilities/api_utils.py
aether_shared/utilities/firebase_utils.py
aether_shared/utilities/geometry_utils.py
aether_shared/utilities/geotiff_utils.py
aether_shared/utilities/local_file_cache.py
aether_shared/utilities/mgrs_utils.py
aether_shared/utilities/services_util.py
aether_shared/utilities/sky_app_utils.py
aether_shared/utilities/user_api_utils.py
api/__init__.py
api/api_entry.py
api/resource_manager.py
api/applications/GeoTiffSampleApp.py
api/applications/MachineLearningApp.py
aether-0.3.37.dist-info/LICENSE.txt
aether-0.3.37.dist-info/METADATA
aether-0.3.37.dist-info/WHEEL
aether-0.3.37.dist-info/top_level.txt
aether-0.3.37.dist-info/RECORD
