Metadata-Version: 2.1
Name: aether
Version: 0.3.37
Summary: Welcome to the Aether Platform
Home-page: https://davidbernat.github.io/aether-user/html/index.html
Author: David Bernat
Author-email: david@starlight.ai
License: UNKNOWN
Keywords: satellite,imagery,remote sensing,starlight,platform,gis
Platform: UNKNOWN
Classifier: Development Status :: 3 - Alpha
Classifier: Intended Audience :: Developers
Classifier: Intended Audience :: Science/Research
Classifier: Topic :: Scientific/Engineering :: GIS
Classifier: Topic :: Scientific/Engineering :: Atmospheric Science
Classifier: Topic :: Scientific/Engineering :: Information Analysis
Classifier: Topic :: Scientific/Engineering :: Physics
Classifier: License :: OSI Approved :: MIT License
Classifier: Programming Language :: Python :: 2.7
Classifier: Programming Language :: Python :: 3.2
Classifier: Programming Language :: Python :: 3.5
Classifier: Programming Language :: Python :: 3.6
Requires-Dist: dill
Requires-Dist: geocoder
Requires-Dist: utm
Requires-Dist: pyshp
Requires-Dist: Pillow
Requires-Dist: Shapely
Requires-Dist: aenum
Requires-Dist: numpy
Requires-Dist: pyproj
Requires-Dist: rasterio
Requires-Dist: six
Requires-Dist: tifffile
Requires-Dist: geojson
Requires-Dist: fiona
Requires-Dist: tensorflow
Requires-Dist: tensorboard
Requires-Dist: oauth2client
